Metadata-Version: 1.0
Name: DSRE
Version: 0.2
Summary: DSRE package
Home-page: https://gitee.com/meilincao/re.git
Author: cml
Author-email: 1527449673@qq.com
License: UNKNOWN
Platform: UNKNOWN
